fastapi_auth_tortoise_models/__init__.py
fastapi_auth_tortoise_models/models.py
fastapi_auth_tortoise_models/repositories.py
fastapi_auth_tortoise_models-0.0.6.dist-info/METADATA
fastapi_auth_tortoise_models-0.0.6.dist-info/WHEEL
fastapi_auth_tortoise_models-0.0.6.dist-info/licenses/LICENSE
fastapi_auth_tortoise_models-0.0.6.dist-info/RECORD
